[{"company":"Oyoloo","position":"Administrative Assistant I","jobLocation":"Ribeira Grande","jobStatus":"declined","jobType":"part-time","createdAt":"11/23/2023"},
{"company":"Kazio","position":"Financial Advisor","jobLocation":"Ronfe","jobStatus":"declined","jobType":"full-time","createdAt":"11/25/2023"},
{"company":"Tazzy","position":"Food Chemist","jobLocation":"Haputale","jobStatus":"declined","jobType":"full-time","createdAt":"5/10/2023"},
{"company":"Mydeo","position":"Associate Professor","jobLocation":"Rokem Barat","jobStatus":"pending","jobType":"full-time","createdAt":"1/29/2024"},
{"company":"Kazio","position":"Help Desk Technician","jobLocation":"San Francisco","jobStatus":"declined","jobType":"full-time","createdAt":"12/17/2023"},
{"company":"Thoughtworks","position":"Food Chemist","jobLocation":"Castro Barros","jobStatus":"interview","jobType":"internship","createdAt":"1/15/2024"},
{"company":"Livefish","position":"Paralegal","jobLocation":"Pueblo","jobStatus":"declined","jobType":"internship","createdAt":"3/20/2023"},
{"company":"Jaxworks","position":"Database Administrator IV","jobLocation":"Santa Elena","jobStatus":"interview","jobType":"internship","createdAt":"6/25/2023"},
{"company":"Browsecat","position":"Administrative Assistant I","jobLocation":"Yangchun","jobStatus":"declined","jobType":"internship","createdAt":"12/9/2023"},
{"company":"Wikizz","position":"Environmental Specialist","jobLocation":"Jiehu","jobStatus":"interview","jobType":"full-time","createdAt":"9/28/2023"},
{"company":"Buzzbean","position":"Nuclear Power Engineer","jobLocation":"Lobito","jobStatus":"interview","jobType":"internship","createdAt":"7/4/2023"},
{"company":"Dabshots","position":"Staff Accountant IV","jobLocation":"Berestechko","jobStatus":"interview","jobType":"part-time","createdAt":"3/26/2023"},
{"company":"Jabbercube","position":"Systems Administrator II","jobLocation":"Sancang","jobStatus":"declined","jobType":"part-time","createdAt":"3/8/2023"},
{"company":"Topiczoom","position":"Media Manager I","jobLocation":"Cikole","jobStatus":"pending","jobType":"part-time","createdAt":"7/10/2023"},
{"company":"Gigaclub","position":"Systems Administrator II","jobLocation":"Onguday","jobStatus":"pending","jobType":"internship","createdAt":"12/2/2023"},
{"company":"Jabbersphere","position":"Graphic Designer","jobLocation":"Accha","jobStatus":"pending","jobType":"full-time","createdAt":"8/28/2023"},
{"company":"Aimbu","position":"Safety Technician I","jobLocation":"Nyandoma","jobStatus":"declined","jobType":"internship","createdAt":"2/10/2023"},
{"company":"Edgetag","position":"Project Manager","jobLocation":"Qingyuan","jobStatus":"declined","jobType":"full-time","createdAt":"6/20/2023"},
{"company":"Edgetag","position":"Social Worker","jobLocation":"Manquiring","jobStatus":"declined","jobType":"full-time","createdAt":"5/30/2023"},
{"company":"Yakidoo","position":"Recruiter","jobLocation":"Phak Hai","jobStatus":"declined","jobType":"internship","createdAt":"6/10/2023"},
{"company":"Feednation","position":"Programmer IV","jobLocation":"Gävle","jobStatus":"interview","jobType":"full-time","createdAt":"12/10/2023"},
{"company":"Babbleopia","position":"Occupational Therapist","jobLocation":"Winneba","jobStatus":"interview","jobType":"internship","createdAt":"4/2/2023"},
{"company":"Kamba","position":"Chemical Engineer","jobLocation":"Beaufort","jobStatus":"interview","jobType":"internship","createdAt":"8/6/2023"},
{"company":"Buzzster","position":"Engineer I","jobLocation":"Curahuasi","jobStatus":"pending","jobType":"full-time","createdAt":"8/2/2023"},
{"company":"Twitterbeat","position":"Design Engineer","jobLocation":"Tuanjie","jobStatus":"declined","jobType":"internship","createdAt":"5/4/2023"},
{"company":"Meedoo","position":"Chemical Engineer","jobLocation":"Milán","jobStatus":"interview","jobType":"full-time","createdAt":"4/4/2023"},
{"company":"Browsedrive","position":"Senior Editor","jobLocation":"Damatulan","jobStatus":"interview","jobType":"internship","createdAt":"10/12/2023"},
{"company":"Devpoint","position":"Project Manager","jobLocation":"Xinzhu","jobStatus":"declined","jobType":"part-time","createdAt":"2/14/2023"},
{"company":"Youbridge","position":"Senior Quality Engineer","jobLocation":"Smolec","jobStatus":"interview","jobType":"full-time","createdAt":"5/31/2023"},
{"company":"Meetz","position":"Environmental Tech","jobLocation":"Otwock","jobStatus":"declined","jobType":"part-time","createdAt":"9/28/2023"},
{"company":"Voolia","position":"Quality Control Specialist","jobLocation":"Willowmore","jobStatus":"interview","jobType":"full-time","createdAt":"7/1/2023"},
{"company":"Edgeclub","position":"Human Resources Manager","jobLocation":"Taipingchuan","jobStatus":"pending","jobType":"part-time","createdAt":"4/15/2023"},
{"company":"Gigaclub","position":"GIS Technical Architect","jobLocation":"Dalar","jobStatus":"declined","jobType":"part-time","createdAt":"7/9/2023"},
{"company":"Voolia","position":"Staff Accountant IV","jobLocation":"Banjarejo","jobStatus":"interview","jobType":"full-time","createdAt":"2/1/2023"},
{"company":"Flashset","position":"Senior Editor","jobLocation":"Sumbe","jobStatus":"interview","jobType":"full-time","createdAt":"4/18/2023"},
{"company":"Flashset","position":"Web Designer II","jobLocation":"Tunbao","jobStatus":"interview","jobType":"part-time","createdAt":"11/11/2023"},
{"company":"Gevee","position":"Budget/Accounting Analyst II","jobLocation":"Barrancas","jobStatus":"interview","jobType":"part-time","createdAt":"10/14/2023"},
{"company":"Mybuzz","position":"Operator","jobLocation":"Khao Kho","jobStatus":"pending","jobType":"part-time","createdAt":"7/29/2023"},
{"company":"Yakidoo","position":"Speech Pathologist","jobLocation":"Pom Prap Sattru Phai","jobStatus":"interview","jobType":"full-time","createdAt":"1/17/2024"},
{"company":"Thoughtbeat","position":"Nuclear Power Engineer","jobLocation":"Tiancheng","jobStatus":"declined","jobType":"part-time","createdAt":"12/24/2023"},
{"company":"Photolist","position":"Media Manager II","jobLocation":"Bulo","jobStatus":"pending","jobType":"internship","createdAt":"11/21/2023"},
{"company":"Tavu","position":"Human Resources Manager","jobLocation":"Cabedelo","jobStatus":"pending","jobType":"full-time","createdAt":"3/10/2023"},
{"company":"Yodo","position":"Quality Control Specialist","jobLocation":"Luleå","jobStatus":"interview","jobType":"internship","createdAt":"7/22/2023"},
{"company":"Rhyloo","position":"Administrative Officer","jobLocation":"Zaki Biam","jobStatus":"interview","jobType":"part-time","createdAt":"4/15/2023"},
{"company":"Rooxo","position":"Civil Engineer","jobLocation":"Ketapang","jobStatus":"pending","jobType":"internship","createdAt":"1/29/2024"},
{"company":"Voolith","position":"Desktop Support Technician","jobLocation":"Kandun","jobStatus":"declined","jobType":"full-time","createdAt":"11/14/2023"},
{"company":"Gigashots","position":"Structural Engineer","jobLocation":"Qiaolin","jobStatus":"pending","jobType":"full-time","createdAt":"2/3/2023"},
{"company":"Youspan","position":"Editor","jobLocation":"Corral de Bustos","jobStatus":"interview","jobType":"full-time","createdAt":"6/25/2023"},
{"company":"Chatterpoint","position":"Food Chemist","jobLocation":"Ilovka","jobStatus":"pending","jobType":"full-time","createdAt":"8/22/2023"},
{"company":"Zoonoodle","position":"Administrative Officer","jobLocation":"Zargarān","jobStatus":"declined","jobType":"full-time","createdAt":"5/17/2023"},
{"company":"Jaxbean","position":"Information Systems Manager","jobLocation":"Andrijaševci","jobStatus":"interview","jobType":"part-time","createdAt":"8/6/2023"},
{"company":"Wikibox","position":"Marketing Assistant","jobLocation":"Balīlā","jobStatus":"pending","jobType":"part-time","createdAt":"7/17/2023"},
{"company":"Gabtype","position":"Budget/Accounting Analyst III","jobLocation":"Karano","jobStatus":"declined","jobType":"part-time","createdAt":"12/18/2023"},
{"company":"Mynte","position":"Chemical Engineer","jobLocation":"Hongshanyao","jobStatus":"interview","jobType":"full-time","createdAt":"1/15/2024"},
{"company":"Photofeed","position":"Software Test Engineer III","jobLocation":"Veruela","jobStatus":"declined","jobType":"internship","createdAt":"2/24/2023"},
{"company":"Zoonoodle","position":"Product Engineer","jobLocation":"Kliteh","jobStatus":"interview","jobType":"internship","createdAt":"5/19/2023"},
{"company":"Bluezoom","position":"Actuary","jobLocation":"Tongyu","jobStatus":"pending","jobType":"internship","createdAt":"12/26/2023"},
{"company":"Pixope","position":"Recruiter","jobLocation":"Borino","jobStatus":"pending","jobType":"part-time","createdAt":"9/17/2023"},
{"company":"Meedoo","position":"Account Representative III","jobLocation":"Cunliji","jobStatus":"pending","jobType":"full-time","createdAt":"2/19/2023"},
{"company":"Tagpad","position":"Database Administrator I","jobLocation":"Yangping","jobStatus":"declined","jobType":"internship","createdAt":"11/25/2023"},
{"company":"Skilith","position":"Developer I","jobLocation":"Pinsk","jobStatus":"pending","jobType":"part-time","createdAt":"10/12/2023"},
{"company":"Realbuzz","position":"Web Designer IV","jobLocation":"Severka","jobStatus":"interview","jobType":"full-time","createdAt":"2/22/2023"},
{"company":"Babbleblab","position":"Programmer Analyst I","jobLocation":"San Juan","jobStatus":"interview","jobType":"part-time","createdAt":"4/6/2023"},
{"company":"Skivee","position":"Structural Analysis Engineer","jobLocation":"Kurbnesh","jobStatus":"declined","jobType":"internship","createdAt":"3/15/2023"},
{"company":"Mita","position":"Safety Technician II","jobLocation":"Sruki","jobStatus":"interview","jobType":"full-time","createdAt":"9/29/2023"},
{"company":"Jetpulse","position":"Structural Analysis Engineer","jobLocation":"Lamam","jobStatus":"interview","jobType":"part-time","createdAt":"1/26/2024"},
{"company":"Roombo","position":"Software Test Engineer III","jobLocation":"Týn nad Vltavou","jobStatus":"pending","jobType":"full-time","createdAt":"10/29/2023"},
{"company":"Aimbu","position":"Marketing Manager","jobLocation":"Peer","jobStatus":"interview","jobType":"full-time","createdAt":"1/2/2024"},
{"company":"Pixoboo","position":"Web Developer III","jobLocation":"Kardamás","jobStatus":"declined","jobType":"internship","createdAt":"2/23/2023"},
{"company":"Yoveo","position":"Internal Auditor","jobLocation":"Clermont-Ferrand","jobStatus":"interview","jobType":"full-time","createdAt":"7/17/2023"},
{"company":"Eadel","position":"Quality Control Specialist","jobLocation":"Campos Sales","jobStatus":"pending","jobType":"full-time","createdAt":"2/8/2023"},
{"company":"Youspan","position":"Mechanical Systems Engineer","jobLocation":"Benjamin Constant","jobStatus":"interview","jobType":"part-time","createdAt":"1/30/2024"},
{"company":"Kare","position":"Account Executive","jobLocation":"Plalar","jobStatus":"interview","jobType":"internship","createdAt":"9/27/2023"},
{"company":"Jabbersphere","position":"Technical Writer","jobLocation":"Malaya Dubna","jobStatus":"declined","jobType":"internship","createdAt":"10/19/2023"},
{"company":"Yacero","position":"Accountant I","jobLocation":"Makumbako","jobStatus":"pending","jobType":"internship","createdAt":"2/27/2023"},
{"company":"Gigazoom","position":"Human Resources Manager","jobLocation":"Tangshan","jobStatus":"declined","jobType":"internship","createdAt":"9/9/2023"},
{"company":"Eadel","position":"Recruiter","jobLocation":"Khovd","jobStatus":"declined","jobType":"part-time","createdAt":"10/30/2023"},
{"company":"Feedspan","position":"Recruiting Manager","jobLocation":"Seshcha","jobStatus":"pending","jobType":"internship","createdAt":"8/5/2023"},
{"company":"Twitterlist","position":"VP Marketing","jobLocation":"Kang-neung","jobStatus":"interview","jobType":"full-time","createdAt":"7/16/2023"},
{"company":"Jabberstorm","position":"Pharmacist","jobLocation":"Pitanga","jobStatus":"pending","jobType":"internship","createdAt":"4/4/2023"},
{"company":"Oyoloo","position":"Pharmacist","jobLocation":"Camangcamang","jobStatus":"pending","jobType":"internship","createdAt":"10/29/2023"},
{"company":"Jabberstorm","position":"Engineer II","jobLocation":"Penambangan","jobStatus":"interview","jobType":"full-time","createdAt":"7/27/2023"},
{"company":"Oyondu","position":"Payment Adjustment Coordinator","jobLocation":"Santa María de Caparo","jobStatus":"interview","jobType":"internship","createdAt":"11/29/2023"},
{"company":"Latz","position":"Compensation Analyst","jobLocation":"Santo Niño","jobStatus":"interview","jobType":"part-time","createdAt":"10/2/2023"},
{"company":"Tazzy","position":"Office Assistant III","jobLocation":"Kinkala","jobStatus":"pending","jobType":"full-time","createdAt":"5/4/2023"},
{"company":"Ooba","position":"Operator","jobLocation":"Non Sung","jobStatus":"interview","jobType":"internship","createdAt":"3/19/2023"},
{"company":"Photospace","position":"Paralegal","jobLocation":"Zhushan Chengguanzhen","jobStatus":"interview","jobType":"part-time","createdAt":"2/25/2023"},
{"company":"BlogXS","position":"Chemical Engineer","jobLocation":"Thap Khlo","jobStatus":"pending","jobType":"internship","createdAt":"5/18/2023"},
{"company":"Jabbersphere","position":"Accounting Assistant I","jobLocation":"Pinoma","jobStatus":"declined","jobType":"internship","createdAt":"2/16/2023"},
{"company":"Devify","position":"Web Developer I","jobLocation":"Villa Ascasubi","jobStatus":"interview","jobType":"part-time","createdAt":"10/30/2023"},
{"company":"Realcube","position":"Clinical Specialist","jobLocation":"Longqiao","jobStatus":"interview","jobType":"part-time","createdAt":"2/19/2023"},
{"company":"Edgetag","position":"Financial Analyst","jobLocation":"Djibouti","jobStatus":"interview","jobType":"full-time","createdAt":"3/10/2023"},
{"company":"Twinder","position":"Professor","jobLocation":"Rancabungur","jobStatus":"declined","jobType":"internship","createdAt":"1/10/2024"},
{"company":"Skimia","position":"Senior Cost Accountant","jobLocation":"Matola","jobStatus":"interview","jobType":"internship","createdAt":"1/22/2024"},
{"company":"Quatz","position":"Nuclear Power Engineer","jobLocation":"Markova","jobStatus":"declined","jobType":"part-time","createdAt":"1/18/2024"},
{"company":"Lazzy","position":"Senior Sales Associate","jobLocation":"Sukhothai","jobStatus":"declined","jobType":"internship","createdAt":"2/3/2023"},
{"company":"Skimia","position":"Community Outreach Specialist","jobLocation":"Kokkini Trimithia","jobStatus":"pending","jobType":"part-time","createdAt":"7/13/2023"},
{"company":"Browsebug","position":"Business Systems Development Analyst","jobLocation":"Marseille","jobStatus":"declined","jobType":"full-time","createdAt":"2/19/2023"},
{"company":"Dynava","position":"VP Accounting","jobLocation":"Mirsíni","jobStatus":"declined","jobType":"part-time","createdAt":"10/13/2023"},
{"company":"Avamba","position":"Help Desk Operator","jobLocation":"Cruzeiro","jobStatus":"interview","jobType":"part-time","createdAt":"4/5/2023"}
]
